mitosisanalyzer/__init__.py
mitosisanalyzer/analysis.py
mitosisanalyzer/calc.py
mitosisanalyzer/fileutils.py
mitosisanalyzer/segmentation.py
mitosisanalyzer/vis.py
mitosisanalyzer-0.0.1.dist-info/METADATA
mitosisanalyzer-0.0.1.dist-info/WHEEL
mitosisanalyzer-0.0.1.dist-info/entry_points.txt
mitosisanalyzer-0.0.1.dist-info/licenses/LICENSE
mitosisanalyzer-0.0.1.dist-info/RECORD
