Metadata-Version: 2.4
Name: mitosisanalyzer
Version: 0.0.1
Summary: Tool to track spindle pole movements in fluorescently labeled mitotic cells.
Project-URL: Homepage, https://github.com/uvarc/mitosisanalyzer
Project-URL: Issues, https://github.com/uvarc/mitosisanalyzer/issues
Author: Karsten Siller
License: 
License-File: LICENSE
Classifier: Programming Language :: Python :: 3
Requires-Python: >=3.9
Requires-Dist: argparse
Requires-Dist: cellpose
Requires-Dist: ffmpeg
Requires-Dist: matplotlib
Requires-Dist: nd2reader
Requires-Dist: opencv-python-headless
Requires-Dist: pandas
Requires-Dist: prefect
Requires-Dist: prefect-dask
Requires-Dist: scikit-image
Requires-Dist: scipy
Requires-Dist: seaborn
Requires-Dist: tifffile
Requires-Dist: tiffile
Requires-Dist: typing
Provides-Extra: napari
Requires-Dist: mitosisanalyzer-napari; extra == 'napari'
